[
   {
      "id": "id0",
      "value": "ARLD00000",
      "label": "Administração de Rede Longa Distância",
      "childs": [
         {
            "id": "id01",
            "value": "ARLD00100|MapaVisaoGeralPortalMODELO",
            "label": "Gerência Rede"
         },
         {
            "id": "id02",
            "value": "ARLD00200|TopologiaWANPortalMODELO",
            "label": "Topologia"
         },
         {
            "id": "id03",
            "value": "ARLD00300",
            "label": "Informações Circuitos e Roteadores",
            "childs": [
               {
                  "id": "id031",
                  "value": "ARLD00300|InformacoesCircuitosRoteadoresMODELO",
                  "label": "Diário"
               },
               {
                  "id": "id032",
                  "value": "ARLD00300|IndicadoresDesempenhoWANNacionalMODELO",
                  "label": "Mensal"
               }
            ]
         },
         {
            "id": "id04",
            "value": "ARLD00400|OcupacaoBandaTrimestralMODELO",
            "label": "Alta Utilização Persistente"
         }
      ]
   },
   {
      "id": "id1",
      "value": "ARL00000",
      "label": "Administração de Rede Local",
      "childs": [
         {
            "id": "id11",
            "value": "ARL00100|TopologiaLANPortalMODELO",
            "label": "Topologia"
         },
         {
            "id": "id12",
            "value": "ARL00200|GerenciaWIFIPortalMODELO",
            "label": "Wifi"
         }
      ]
   },
   {
      "id": "id2",
      "value": "INF00000",
      "label": "Infovia",
      "childs": [
         {
            "id": "id21",
            "value": "INF00100|DisponibilidadeInfoviaMODELO",
            "label": "INF00100|Monitoração"
         }
      ]
   },
   {
      "id": "id3",
      "value": "ING00000",
      "label": "Informações Gerenciais",
      "childs": [
         {
            "id": "id31",
            "value": "ING00100|Ambiente",
            "label": "Ambiente",
            "childs": [
               {
                  "id": "id311",
                  "value": "ING00106|CertificadoDigitalPlanilhaXLSMODELO",
                  "label": "Certificado Digital Planilha"
               },
               {
                  "id": "id312",
                  "value": "ING00101|RelatorioPDFMODELO",
                  "label": "Datacenter"
               },
               {
                  "id": "id313",
                  "value": "ING00102|RelatorioPDFMODELO",
                  "label": "Infovia"
               },
               {
                  "id": "id314",
                  "value": "ING00103|RelatorioPDFLANMODELOJURIS",
                  "label": "Lan Juridiscionante"
               },
               {
                  "id": "id315",
                  "value": "ING00104|RelatorioPDFMODELO",
                  "label": "Lan"
               },
               {
                  "id": "id316",
                  "value": "ING00105|RelatorioPDFMODELO",
                  "label": "Wan"
               }
            ]
         }
      ]
   },
   {
      "id": "id4",
      "value": "ING00300",
      "label": "Documentos",
      "childs": [
         {
            "id": "id41",
            "value": "ING00300|InformativoPDFMODELO",
            "label": "Informativo"
         },
         {
            "id": "id42",
            "value": "ING00301|DocumentosPDFMODELO",
            "label": "Manuais"
         },
         {
            "id": "id43",
            "value": "ING00302|DocumentosPDFMODELO",
            "label": "Modelos Tecnológicos"
         }
      ]
   },
   {
      "id": "id5",
      "value": "ING00400|PlantaInstaladaMODELO",
      "label": "Planta Instalada"
   },
   {
      "id": "id6",
      "value": "ING00500|PlantaInstaladaMODELO",
      "label": "Segurança",
      "childs": [
         {
            "id": "id61",
            "value": "ING00501|RelatorioPDFMODELO",
            "label": "AntiDDOS"
         },
         {
            "id": "id62",
            "value": "ING00502|RelatorioPDFMODELO",
            "label": "FIREWALL"
         },
         {
            "id": "id63",
            "value": "ING00503|RelatorioPDFMODELO",
            "label": "IPS"
         }
      ]
   },
   {
      "id": "id7",
      "value": "MDP00000",
      "label": "Monitoração por Demanda",
      "childs": [
         {
            "id": "id71",
            "value": "MPD00100|MonitoracaoDemandaMODELO",
            "label": "Painel 1"
         }
      ]
   }
]